DCO
LICENSE
MAINTAINERS
MANIFEST.in
README.md
requirements.txt
setup.py
bblfsh_sonar_checks/__init__.py
bblfsh_sonar_checks/__main__.py
bblfsh_sonar_checks/utils.py
bblfsh_sonar_checks.egg-info/PKG-INFO
bblfsh_sonar_checks.egg-info/SOURCES.txt
bblfsh_sonar_checks.egg-info/dependency_links.txt
bblfsh_sonar_checks.egg-info/entry_points.txt
bblfsh_sonar_checks.egg-info/requires.txt
bblfsh_sonar_checks.egg-info/top_level.txt
bblfsh_sonar_checks/checks/__init__.py
bblfsh_sonar_checks/checks/java/RSPEC-1143.py
bblfsh_sonar_checks/checks/java/RSPEC-1174.py
bblfsh_sonar_checks/checks/java/RSPEC-1201.py
bblfsh_sonar_checks/checks/java/RSPEC-1214.py
bblfsh_sonar_checks/checks/java/RSPEC-1215.py
bblfsh_sonar_checks/checks/java/RSPEC-1217.py
bblfsh_sonar_checks/checks/java/RSPEC-1221.py
bblfsh_sonar_checks/checks/java/RSPEC-128.py
bblfsh_sonar_checks/checks/java/RSPEC-131.py
bblfsh_sonar_checks/checks/java/RSPEC-1317.py
bblfsh_sonar_checks/checks/java/RSPEC-1764.py
bblfsh_sonar_checks/checks/java/RSPEC-1845.py
bblfsh_sonar_checks/checks/java/RSPEC-1862.py
bblfsh_sonar_checks/checks/java/RSPEC-1872.py
bblfsh_sonar_checks/checks/java/RSPEC-1994.py
bblfsh_sonar_checks/checks/java/RSPEC-2062.py
bblfsh_sonar_checks/checks/java/RSPEC-2068.py
bblfsh_sonar_checks/checks/java/RSPEC-2122.py
bblfsh_sonar_checks/checks/java/RSPEC-2151.py
bblfsh_sonar_checks/checks/java/RSPEC-2157.py
bblfsh_sonar_checks/checks/java/RSPEC-2176.py
bblfsh_sonar_checks/checks/java/RSPEC-2178.py
bblfsh_sonar_checks/checks/java/RSPEC-2225.py
bblfsh_sonar_checks/checks/java/RSPEC-2226.py
bblfsh_sonar_checks/checks/java/RSPEC-2235.py
bblfsh_sonar_checks/checks/java/RSPEC-2273.py
bblfsh_sonar_checks/checks/java/RSPEC-2275.py
bblfsh_sonar_checks/checks/java/RSPEC-2276.py
bblfsh_sonar_checks/checks/java/RSPEC-2277.py
bblfsh_sonar_checks/checks/java/RSPEC-2278.py
bblfsh_sonar_checks/checks/java/RSPEC-2387.py
bblfsh_sonar_checks/checks/java/RSPEC-2390.py
bblfsh_sonar_checks/checks/java/RSPEC-2437.py
bblfsh_sonar_checks/checks/java/RSPEC-2446.py
bblfsh_sonar_checks/checks/java/RSPEC-2447.py
bblfsh_sonar_checks/checks/java/RSPEC-2653.py
bblfsh_sonar_checks/checks/java/RSPEC-2692.py
bblfsh_sonar_checks/checks/java/RSPEC-2757.py
bblfsh_sonar_checks/checks/java/RSPEC-2761.py
