Metadata-Version: 1.1
Name: bblfsh-sonar-checks
Version: 0.4.0
Summary: Library implementing Sonar Source checks using the babelfish project
Home-page: https://github.com/bblfsh/sonar_source_checks
Author: source{d}
Author-email: language-analysis@sourced.tech
License: Apache 2.0
Download-URL: https://github.com/bblfsh/sonar_source_checks
Keywords: babelfish,uast,static analysis,java
Platform: UNKNOWN
Classifier: Development Status :: 3 - Alpha
Classifier: Environment :: Console
Classifier: Intended Audience :: Developers
Classifier: License :: OSI Approved :: Apache Software License
Classifier: Operating System :: POSIX
Classifier: Programming Language :: Python :: 3.4
Classifier: Programming Language :: Python :: 3.5
Classifier: Programming Language :: Python :: 3.6
Classifier: Programming Language :: Python :: 3.7
Classifier: Topic :: Software Development :: Libraries
